e2hbaseapi/__init__.py
e2hbaseapi/client.py
e2hbaseapi-0.2.1.dist-info/LICENSE
e2hbaseapi-0.2.1.dist-info/METADATA
e2hbaseapi-0.2.1.dist-info/WHEEL
e2hbaseapi-0.2.1.dist-info/top_level.txt
e2hbaseapi-0.2.1.dist-info/RECORD
