Metadata-Version: 2.1
Name: e2hbaseapi
Version: 0.2.1
Summary: A Python package for interacting with E2hbaseapi and extracting specific information.
Author: E2H
License: MIT
Classifier: Programming Language :: Python :: 3
Classifier: License :: OSI Approved :: MIT License
Classifier: Programming Language :: Python :: 3.7
Classifier: Programming Language :: Python :: 3.8
Classifier: Programming Language :: Python :: 3.9
Classifier: Programming Language :: Python :: 3.10
Classifier: Programming Language :: Python :: 3.11
Classifier: Programming Language :: Python :: 3.12
License-File: LICENSE
Requires-Dist: elasticsearch
Requires-Dist: regex
Requires-Dist: urllib3
Requires-Dist: tenacity
Requires-Dist: pydantic
Requires-Dist: pydantic[email]
